MANIFEST.in
setup.py
bin/__init__.py
bin/__init__.pyc
bin/lemmatize.py
bin/lowercase.py
bin/tokenizer.py
nlpy/__init__.py
nlpy/__init__.pyc
nlpy/server.py
nlpy.egg-info/PKG-INFO
nlpy.egg-info/SOURCES.txt
nlpy.egg-info/dependency_links.txt
nlpy.egg-info/requires.txt
nlpy.egg-info/top_level.txt
nlpy/basic/__init__.py
nlpy/basic/__init__.pyc
nlpy/basic/abstract_tokenizer.py
nlpy/basic/abstract_tokenizer.pyc
nlpy/basic/contentfulness.py
nlpy/basic/contentfulness.pyc
nlpy/basic/nltk_lemmatizer.py
nlpy/basic/nltk_lemmatizer.pyc
nlpy/basic/nltk_tokenizers.py
nlpy/basic/nltk_tokenizers.pyc
nlpy/basic/recase.py
nlpy/basic/recase.pyc
nlpy/classification/__init__.py
nlpy/classification/__init__.pyc
nlpy/classification/logistic_regression.py
nlpy/classification/logistic_regression.pyc
nlpy/dataset/__init__.py
nlpy/dataset/__init__.pyc
nlpy/dataset/abstract_dataset.py
nlpy/dataset/abstract_dataset.pyc
nlpy/dataset/heart_scale.py
nlpy/dataset/heart_scale.pyc
nlpy/dataset/mini_batch.py
nlpy/dataset/mini_batch.pyc
nlpy/dataset/mnist.py
nlpy/dataset/mnist.pyc
nlpy/deep/__init__.py
nlpy/deep/__init__.pyc
nlpy/deep/functions.py
nlpy/deep/functions.pyc
nlpy/deep/nnprocessors.py
nlpy/deep/nnprocessors.pyc
nlpy/deep/conf/__init__.py
nlpy/deep/conf/__init__.pyc
nlpy/deep/conf/nn_config.py
nlpy/deep/conf/nn_config.pyc
nlpy/deep/conf/trainer_config.py
nlpy/deep/conf/trainer_config.pyc
nlpy/deep/networks/__init__.py
nlpy/deep/networks/__init__.pyc
nlpy/deep/networks/auto_encoder.py
nlpy/deep/networks/auto_encoder.pyc
nlpy/deep/networks/basic_nn.py
nlpy/deep/networks/basic_nn.pyc
nlpy/deep/networks/classifier.py
nlpy/deep/networks/classifier.pyc
nlpy/deep/networks/classifier_runner.py
nlpy/deep/networks/classifier_runner.pyc
nlpy/deep/networks/conv.py
nlpy/deep/networks/conv.pyc
nlpy/deep/networks/layer.py
nlpy/deep/networks/layer.pyc
nlpy/deep/networks/lstm.py
nlpy/deep/networks/lstm.pyc
nlpy/deep/networks/mlp.py
nlpy/deep/networks/recurrent.py
nlpy/deep/networks/recurrent.pyc
nlpy/deep/networks/recursive.py
nlpy/deep/networks/recursive.pyc
nlpy/deep/networks/regressor.py
nlpy/deep/networks/regressor.pyc
