Metadata-Version: 1.0
Name: nlpy
Version: 0.0.7
Summary: Natural Language Processing on Python
Home-page: http://nlpy.org
Author: Raphael Shu
Author-email: raphael@uaca.com
License: LGPL
Download-URL: http://pypi.python.org/pypi/nlpy
Keywords: Natural Language Processing  Natural Language Understanding  Semantic Representation  Machine Translation
Platform: any
Classifier: Development Status :: 2 - Pre-Alpha
Classifier: Environment :: Console
Classifier: Intended Audience :: Science/Research
Classifier: License :: OSI Approved :: GNU Library or Lesser General Public License (LGPL)
Classifier: Operating System :: OS Independent
Classifier: Programming Language :: Python :: 2.6
Classifier: Programming Language :: Python :: 2.7
Classifier: Programming Language :: Python :: 3.4
Classifier: Topic :: Scientific/Engineering :: Artificial Intelligence
Classifier: Topic :: Scientific/Engineering :: Information Analysis
Classifier: Topic :: Text Processing :: Linguistic
